{
   "check_word" : "_o___",
   "game_id" : "65071367_0000",
   "guesses" : {
      "data" : [
         {
            "guess" : "earth",
            "result" : "oo___",
            "time" : "0000"
         },
         {
            "guess" : "mound",
            "result" : "_____",
            "time" : "0000"
         },
         {
            "guess" : "sicky",
            "result" : "_____",
            "time" : "0000"
         },
         {
            "guess" : "mafia",
            "result" : "_o___",
            "time" : "0000"
         }
      ]
   },
   "remaining_score" : 96,
   "score_distributed" : false,
   "word" : "glaze"
}
