{
   "check_word" : "__o__",
   "game_id" : "84530310_0000",
   "guesses" : {
      "data" : [
         {
            "guess" : "earth",
            "result" : "o__o_",
            "time" : "0000"
         },
         {
            "guess" : "mound",
            "result" : "__o_o",
            "time" : "0000"
         },
         {
            "guess" : "sicky",
            "result" : "_____",
            "time" : "0000"
         },
         {
            "guess" : "mafia",
            "result" : "_____",
            "time" : "0000"
         },
         {
            "guess" : "agape",
            "result" : "____o",
            "time" : "0000"
         },
         {
            "guess" : "djins",
            "result" : "#____",
            "time" : "0000"
         },
         {
            "guess" : "above",
            "result" : "_o__o",
            "time" : "0000"
         },
         {
            "guess" : "ablow",
            "result" : "_o___",
            "time" : "0000"
         },
         {
            "guess" : "abuzz",
            "result" : "_oo__",
            "time" : "0000"
         },
         {
            "guess" : "abbey",
            "result" : "__#o_",
            "time" : "0000"
         },
         {
            "guess" : "aquas",
            "result" : "__o__",
            "time" : "0000"
         }
      ]
   },
   "remaining_score" : 89,
   "score_distributed" : false,
   "word" : "debut"
}
